user_notifications/__init__.py
user_notifications/__version__.py
user_notifications/admin.py
user_notifications/apps.py
user_notifications/models.py
user_notifications/rules.py
user_notifications/utils.py
user_notifications/migrations/0001_initial.py
user_notifications/migrations/0002_alter_notification_display_type.py
user_notifications/migrations/0003_alter_notification_display_type.py
user_notifications/migrations/0004_alter_notification_display_type.py
user_notifications/migrations/__init__.py
user_notifications/templates/user_notifications/messages.html
user_notifications/tests/__init__.py
user_notifications/tests/example_rules.py
user_notifications/tests/test_notification.py
user_notifications/tests/test_rules.py
django_user_notifications-0.1.14.dist-info/LICENSE
django_user_notifications-0.1.14.dist-info/METADATA
django_user_notifications-0.1.14.dist-info/WHEEL
django_user_notifications-0.1.14.dist-info/top_level.txt
django_user_notifications-0.1.14.dist-info/RECORD
