Metadata-Version: 2.1
Name: django-user-notifications
Version: 0.1.14
Summary: Django App that extendes django-user-messages for createing easy user notifications based user set rules.
Home-page: https://github.com/rhimmelbauer/django-user-notifications/
Author: Roberto Himmelbauer
Author-email: robertoh89@gmail.com
License: MIT license
Keywords: django,app,messages
Platform: UNKNOWN
Classifier: Development Status :: 2 - Pre-Alpha
Classifier: Intended Audience :: Developers
Classifier: Programming Language :: Python :: 3 :: Only
Classifier: Programming Language :: Python :: 3.8
Requires-Python: >=3.7
License-File: LICENSE
Requires-Dist: Django<4.0,>=3.0
Requires-Dist: django-autoslug
Requires-Dist: django-extensions
Requires-Dist: django-user-messages
Requires-Dist: iso4217
Provides-Extra: build
Requires-Dist: setuptools; extra == "build"
Requires-Dist: wheel; extra == "build"
Requires-Dist: twine; extra == "build"
Requires-Dist: m2r; extra == "build"
Requires-Dist: keyrings.google-artifactregistry-auth; extra == "build"
Provides-Extra: dev
Requires-Dist: dj-database-url; extra == "dev"
Requires-Dist: psycopg2-binary; extra == "dev"
Requires-Dist: django-crispy-forms; extra == "dev"
Requires-Dist: django-allauth; extra == "dev"
Provides-Extra: docs
Requires-Dist: recommonmark; extra == "docs"
Requires-Dist: m2r; extra == "docs"
Requires-Dist: django-extensions; extra == "docs"
Requires-Dist: coverage; extra == "docs"
Requires-Dist: Sphinx; extra == "docs"
Requires-Dist: rstcheck; extra == "docs"
Requires-Dist: sphinx-rtd-theme; extra == "docs"
Provides-Extra: prod
Provides-Extra: test
